{
  "$schema": "https://mintlify.com/docs.json",
  "name": "ScoreSaber Reloaded",
  "theme": "aspen",
  "colors": {
    "primary": "#f3d520",
    "light": "#7c640c",
    "dark": "#221b1c"
  },
  "favicon": "https://media.brand.dev/6f6ba820-2d91-42ac-9a8a-d3ab7727acd4.png",
  "navbar": {
    "primary": {
      "type": "github",
      "href": "https://github.com/RealFascinated/scoresaber-reloaded"
    }
  },
  "footer": {
    "socials": {
      "github": "https://github.com/RealFascinated/scoresaber-reloaded"
    }
  },
  "navigation": {
    "tabs": [
      {
        "tab": "Documentation",
        "groups": [
          {
            "group": "Overview",
            "pages": ["introduction", "quickstart"]
          },
          {
            "group": "Core Features",
            "pages": [
              "features/player-profiles",
              "features/score-tracking",
              "features/leaderboards",
              "features/statistics",
              "features/medals",
              "features/playlists"
            ]
          },
          {
            "group": "Integrations",
            "pages": [
              "integrations/scoresaber",
              "integrations/beatleader",
              "integrations/beatsaver",
              "integrations/discord"
            ]
          },
          {
            "group": "Architecture",
            "pages": [
              "architecture/overview",
              "architecture/frontend",
              "architecture/backend",
              "architecture/database"
            ]
          }
        ]
      },
      {
        "tab": "API Reference",
        "groups": [
          {
            "group": "Getting Started",
            "pages": ["api/overview", "api/authentication"]
          },
          {
            "group": "Endpoints",
            "pages": [
              "api/player",
              "api/scores",
              "api/leaderboards",
              "api/playlists",
              "api/beatleader",
              "api/beatsaver"
            ]
          }
        ]
      }
    ]
  }
}
